dmtp/__init__.py
dmtp/client.py
dmtp/delegate.py
dmtp/node.py
dmtp/server.py
dmtp/protocol/__init__.py
dmtp/protocol/address.py
dmtp/protocol/command.py
dmtp/protocol/message.py
dmtp/protocol/parsers.py
dmtp/protocol/values.py
dmtp/tlv/__init__.py
dmtp/tlv/field.py
dmtp/tlv/tag.py
dmtp/tlv/value.py
dmtp-0.3.4.dist-info/METADATA
dmtp-0.3.4.dist-info/WHEEL
dmtp-0.3.4.dist-info/top_level.txt
dmtp-0.3.4.dist-info/RECORD
