Metadata-Version: 2.1
Name: dmtp
Version: 0.3.4
Summary: Direct Message Transfer Protocol
Home-page: https://github.com/moky/wormhole/
Author: Albert Moky
Author-email: albert.moky@gmail.com
License: MIT
Platform: UNKNOWN
Classifier: Programming Language :: Python :: 3
Classifier: License :: OSI Approved :: MIT License
Classifier: Operating System :: OS Independent
Requires-Dist: udp (>=0.4.9)
Requires-Dist: stun (>=0.2.3)
